Metadata-Version: 1.0
Name: quepy
Version: 0.1
Summary: A framework to convert natural language to database queries.
Home-page: https://github.com/machinalis/quepy
Author: Rafael Carrascosa, Gonzalo Garcia Berrotaran
Author-email: rafacarrascosa@gmail.com
License: UNKNOWN
Keywords: regular expressions,regexp,re,NLP,natural language processing,natural language interface to database,sparql,database,interface,quepy
Platform: UNKNOWN
Classifier: Programming Language :: Python
Classifier: Development Status :: 3 - Alpha
Classifier: Intended Audience :: Developers
Classifier: Natural Language :: English
Classifier: License :: OSI Approved :: BSD License
Classifier: Operating System :: OS Independent
Classifier: Topic :: Database
Classifier: Topic :: Scientific/Engineering :: Human Machine Interfaces
Classifier: Topic :: Scientific/Engineering :: Interface Engine/Protocol Translator
Classifier: Topic :: Software Development :: Libraries :: Application Frameworks
Classifier: Topic :: Text Processing :: Linguistic
Classifier: Topic :: Text Processing
Classifier: Topic :: Utilities
